proc_shell/__init__.py
proc_shell/proc_shell.py
proc_shell-0.1.1.dist-info/licenses/LICENSE
proc_shell-0.1.1.dist-info/METADATA
proc_shell-0.1.1.dist-info/WHEEL
proc_shell-0.1.1.dist-info/top_level.txt
proc_shell-0.1.1.dist-info/RECORD
