Metadata-Version: 2.4
Name: proc_shell
Version: 0.1.1
Summary: Proc-like subshell temp manager for macOS
Author-email: Your Name <you@example.com>
License: MIT License
Requires-Python: >=3.11
License-File: LICENSE
Requires-Dist: psutil
Dynamic: license-file
